ddmail_backup_receiver/__init__.py
ddmail_backup_receiver/application.py
ddmail_backup_receiver-0.0.2.dist-info/METADATA
ddmail_backup_receiver-0.0.2.dist-info/WHEEL
ddmail_backup_receiver-0.0.2.dist-info/licenses/LICENSE
ddmail_backup_receiver-0.0.2.dist-info/RECORD
